cusb/__init__.py
cusb/__main__.py
cusb/cusb.py
cusb/py.typed
pycusb-0.3.2.dist-info/METADATA
pycusb-0.3.2.dist-info/WHEEL
pycusb-0.3.2.dist-info/entry_points.txt
pycusb-0.3.2.dist-info/licenses/LICENSE
pycusb-0.3.2.dist-info/RECORD
