Metadata-Version: 2.4
Name: pycusb
Version: 0.3.2
Summary: Python implementation of the cusb interface for managed USB hubs
Project-URL: source, https://github.com/gschwaer/pycusb
Project-URL: issues, https://github.com/gschwaer/pycusb
Author-email: Gero Schwäricke <gero.schwaericke@posteo.de>
License-Expression: MIT-0
License-File: LICENSE
Requires-Dist: docopt==0.6.2
Requires-Dist: pyserial==3.5
Provides-Extra: dev
Requires-Dist: pytest; extra == 'dev'
Requires-Dist: pytest-mock; extra == 'dev'
Requires-Dist: types-docopt; extra == 'dev'
Requires-Dist: types-pyserial; extra == 'dev'
